{
  "asOf": "30 Jun 2026 18:01 UTC",
  "sources": {
    "titleOdds": "polymarket",
    "knockoutResults": "polymarket"
  },
  "teams": {
    "MEX": {
      "n": "Mexico",
      "f": "рџ‡Ірџ‡Ѕ",
      "r": 1860
    },
    "RSA": {
      "n": "South Africa",
      "f": "рџ‡їрџ‡¦",
      "r": 1775
    },
    "KOR": {
      "n": "South Korea",
      "f": "рџ‡°рџ‡·",
      "r": 1835
    },
    "CZE": {
      "n": "Czechia",
      "f": "рџ‡Ёрџ‡ї",
      "r": 1820
    },
    "SUI": {
      "n": "Switzerland",
      "f": "рџ‡Ёрџ‡­",
      "r": 1895
    },
    "CAN": {
      "n": "Canada",
      "f": "рџ‡Ёрџ‡¦",
      "r": 1835
    },
    "BIH": {
      "n": "Bosnia & H.",
      "f": "рџ‡§рџ‡¦",
      "r": 1815
    },
    "QAT": {
      "n": "Qatar",
      "f": "рџ‡¶рџ‡¦",
      "r": 1760
    },
    "BRA": {
      "n": "Brazil",
      "f": "рџ‡§рџ‡·",
      "r": 2012
    },
    "MAR": {
      "n": "Morocco",
      "f": "рџ‡Ірџ‡¦",
      "r": 1956
    },
    "HAI": {
      "n": "Haiti",
      "f": "рџ‡­рџ‡№",
      "r": 1660
    },
    "SCO": {
      "n": "Scotland",
      "f": "рџЏґу Ѓ§у Ѓўу Ѓіу ЃЈу Ѓґу Ѓї",
      "r": 1825
    },
    "USA": {
      "n": "USA",
      "f": "рџ‡єрџ‡ё",
      "r": 1973
    },
    "PAR": {
      "n": "Paraguay",
      "f": "рџ‡µрџ‡ѕ",
      "r": 1785
    },
    "AUS": {
      "n": "Australia",
      "f": "рџ‡¦рџ‡є",
      "r": 1800
    },
    "TUR": {
      "n": "Turkiye",
      "f": "рџ‡№рџ‡·",
      "r": 1845
    },
    "GER": {
      "n": "Germany",
      "f": "рџ‡©рџ‡Є",
      "r": 1985
    },
    "CUW": {
      "n": "Curacao",
      "f": "рџ‡Ёрџ‡ј",
      "r": 1640
    },
    "CIV": {
      "n": "Ivory Coast",
      "f": "рџ‡Ёрџ‡®",
      "r": 1860
    },
    "ECU": {
      "n": "Ecuador",
      "f": "рџ‡Єрџ‡Ё",
      "r": 1865
    },
    "NED": {
      "n": "Netherlands",
      "f": "рџ‡ірџ‡±",
      "r": 1995
    },
    "JPN": {
      "n": "Japan",
      "f": "рџ‡Їрџ‡µ",
      "r": 1900
    },
    "SWE": {
      "n": "Sweden",
      "f": "рџ‡ёрџ‡Є",
      "r": 1875
    },
    "TUN": {
      "n": "Tunisia",
      "f": "рџ‡№рџ‡і",
      "r": 1800
    },
    "BEL": {
      "n": "Belgium",
      "f": "рџ‡§рџ‡Є",
      "r": 1945
    },
    "EGY": {
      "n": "Egypt",
      "f": "рџ‡Єрџ‡¬",
      "r": 1815
    },
    "IRN": {
      "n": "Iran",
      "f": "рџ‡®рџ‡·",
      "r": 1815
    },
    "NZL": {
      "n": "New Zealand",
      "f": "рџ‡ірџ‡ї",
      "r": 1680
    },
    "ESP": {
      "n": "Spain",
      "f": "рџ‡Єрџ‡ё",
      "r": 2093
    },
    "CPV": {
      "n": "Cabo Verde",
      "f": "рџ‡Ёрџ‡»",
      "r": 1700
    },
    "KSA": {
      "n": "Saudi Arabia",
      "f": "рџ‡ёрџ‡¦",
      "r": 1760
    },
    "URU": {
      "n": "Uruguay",
      "f": "рџ‡єрџ‡ѕ",
      "r": 1975
    },
    "NOR": {
      "n": "Norway",
      "f": "рџ‡ірџ‡ґ",
      "r": 1971
    },
    "FRA": {
      "n": "France",
      "f": "рџ‡«рџ‡·",
      "r": 2158
    },
    "SEN": {
      "n": "Senegal",
      "f": "рџ‡ёрџ‡і",
      "r": 1910
    },
    "IRQ": {
      "n": "Iraq",
      "f": "рџ‡®рџ‡¶",
      "r": 1720
    },
    "ARG": {
      "n": "Argentina",
      "f": "рџ‡¦рџ‡·",
      "r": 2095
    },
    "ALG": {
      "n": "Algeria",
      "f": "рџ‡©рџ‡ї",
      "r": 1820
    },
    "AUT": {
      "n": "Austria",
      "f": "рџ‡¦рџ‡№",
      "r": 1865
    },
    "JOR": {
      "n": "Jordan",
      "f": "рџ‡Їрџ‡ґ",
      "r": 1700
    },
    "POR": {
      "n": "Portugal",
      "f": "рџ‡µрџ‡№",
      "r": 2061
    },
    "COD": {
      "n": "DR Congo",
      "f": "рџ‡Ёрџ‡©",
      "r": 1785
    },
    "UZB": {
      "n": "Uzbekistan",
      "f": "рџ‡єрџ‡ї",
      "r": 1760
    },
    "COL": {
      "n": "Colombia",
      "f": "рџ‡Ёрџ‡ґ",
      "r": 1951
    },
    "ENG": {
      "n": "England",
      "f": "рџЏґу Ѓ§у Ѓўу ЃҐу Ѓ®у Ѓ§у Ѓї",
      "r": 2056
    },
    "CRO": {
      "n": "Croatia",
      "f": "рџ‡­рџ‡·",
      "r": 1955
    },
    "GHA": {
      "n": "Ghana",
      "f": "рџ‡¬рџ‡­",
      "r": 1805
    },
    "PAN": {
      "n": "Panama",
      "f": "рџ‡µрџ‡¦",
      "r": 1740
    }
  },
  "groupSeeds": {
    "A": [
      "MEX",
      "RSA",
      "KOR"
    ],
    "B": [
      "SUI",
      "CAN",
      "BIH"
    ],
    "C": [
      "BRA",
      "MAR",
      "SCO"
    ],
    "D": [
      "USA",
      "AUS",
      "PAR"
    ],
    "E": [
      "GER",
      "CIV",
      "ECU"
    ],
    "F": [
      "NED",
      "JPN",
      "SWE"
    ],
    "G": [
      "BEL",
      "EGY",
      "IRN"
    ],
    "H": [
      "ESP",
      "CPV",
      "KSA"
    ],
    "I": [
      "FRA",
      "NOR",
      "SEN"
    ],
    "J": [
      "ARG",
      "AUT",
      "ALG"
    ],
    "K": [
      "COL",
      "POR",
      "COD"
    ],
    "L": [
      "ENG",
      "CRO",
      "GHA"
    ]
  },
  "thirdByMatch": {
    "75": "D",
    "78": "F",
    "79": "E",
    "80": "K",
    "81": "I",
    "82": "B",
    "85": "J",
    "88": "L"
  },
  "thirdQual": [
    "B",
    "D",
    "E",
    "F",
    "I",
    "J",
    "K",
    "L"
  ],
  "results": {
    "73": "PAR",
    "75": "CAN",
    "76": "MAR",
    "81": "BRA"
  },
  "marketTitle": {
    "ESP": 0.113,
    "SUI": 0.0085,
    "ENG": 0.0991,
    "FRA": 0.2812,
    "BRA": 0.0702,
    "ARG": 0.1926,
    "COL": 0.0274,
    "POR": 0.0592,
    "GHA": 0.0005,
    "ALG": 0.0015,
    "BIH": 0.0005,
    "USA": 0.0274,
    "CAN": 0.0025,
    "MEX": 0.0164,
    "PAR": 0.0025,
    "NOR": 0.0239,
    "ECU": 0.0055,
    "MAR": 0.0373,
    "SEN": 0.0045,
    "CIV": 0.0025,
    "COD": 0.0005,
    "CPV": 0.0005,
    "BEL": 0.0124,
    "AUS": 0.0015,
    "AUT": 0.0015,
    "CRO": 0.0045,
    "EGY": 0.0015,
    "SWE": 0.0015
  },
  "modelTitle": {
    "FRA": 0.2725,
    "ARG": 0.1912,
    "ESP": 0.1114,
    "ENG": 0.1003,
    "BRA": 0.0674,
    "POR": 0.064,
    "MAR": 0.0392,
    "COL": 0.0276,
    "USA": 0.0245,
    "NOR": 0.0241,
    "BEL": 0.0152,
    "SUI": 0.0099,
    "CRO": 0.0097,
    "SEN": 0.0082,
    "CAN": 0.0055,
    "SWE": 0.0044,
    "ECU": 0.0043,
    "MEX": 0.0034,
    "CIV": 0.0027,
    "PAR": 0.0025,
    "ALG": 0.0024,
    "EGY": 0.0022,
    "AUT": 0.0019,
    "GHA": 0.0018,
    "AUS": 0.0017,
    "BIH": 0.0012,
    "COD": 0.0006,
    "CPV": 0.0001
  },
  "matchOdds": {}
}